cruxctl/__init__.py
cruxctl/command_groups/__init__.py
cruxctl/command_groups/auth/__init__.py
cruxctl/command_groups/auth/auth.py
cruxctl/command_groups/auth/auth_utilities.py
cruxctl/command_groups/dataset/__init__.py
cruxctl/command_groups/dataset/constants.py
cruxctl/command_groups/dataset/dag_run_handler.py
cruxctl/command_groups/dataset/dataset.py
cruxctl/command_groups/dataset/dataset_utils.py
cruxctl/command_groups/dataset/dispatch_run_handler.py
cruxctl/command_groups/dataset/logs_handler.py
cruxctl/command_groups/dataset/models/__init__.py
cruxctl/command_groups/dataset/models/export_activity_type.py
cruxctl/command_groups/dataset_health/__init__.py
cruxctl/command_groups/dataset_health/big_query_dataset_health_repo.py
cruxctl/command_groups/dataset_health/dataset_health.py
cruxctl/command_groups/dataset_health/health_tree_data_adapter.py
cruxctl/command_groups/dataset_health/models/__init__.py
cruxctl/command_groups/dataset_health/models/dataset_health_branch.py
cruxctl/command_groups/dataset_health/models/dataset_health_profile.py
cruxctl/command_groups/dataset_health/postgres_dataset_health_repo.py
cruxctl/command_groups/deadlines/__init__.py
cruxctl/command_groups/deadlines/dataset_deadline_client.py
cruxctl/command_groups/deadlines/dataset_snooze_client.py
cruxctl/command_groups/deadlines/deadline_validations.py
cruxctl/command_groups/deadlines/deadlines.py
cruxctl/command_groups/deadlines/deadlines_snooze.py
cruxctl/command_groups/deadlines/models/__init__.py
cruxctl/command_groups/deadlines/models/dataset_expected_delivery_deadline_columns.py
cruxctl/command_groups/deadlines/models/deadline_notification_snooze_units.py
cruxctl/command_groups/deadlines/models/deadline_row.py
cruxctl/command_groups/profile/__init__.py
cruxctl/command_groups/profile/profile.py
cruxctl/common/__init__.py
cruxctl/common/callbacks.py
cruxctl/common/constants.py
cruxctl/common/data_adapters.py
cruxctl/common/models/__init__.py
cruxctl/common/models/application_profile.py
cruxctl-2.8.0.dist-info/METADATA
cruxctl-2.8.0.dist-info/WHEEL
cruxctl-2.8.0.dist-info/entry_points.txt
cruxctl-2.8.0.dist-info/RECORD
