Metadata-Version: 2.3
Name: cruxctl
Version: 2.8.0
Summary: 
Author: Crux Data
Author-email: help@cruxdata.com
Requires-Python: >=3.10,<3.12
Classifier: Programming Language :: Python :: 3
Classifier: Programming Language :: Python :: 3.10
Classifier: Programming Language :: Python :: 3.11
Requires-Dist: Jinja2 (>=3.1.4,<4.0.0)
Requires-Dist: click (>=8.2.0,<9.0.0)
Requires-Dist: crux-odin (>=1.11.2)
Requires-Dist: google-cloud-bigquery (>=3.23.1,<4.0.0)
Requires-Dist: google-cloud-secret-manager
Requires-Dist: mixpanel
Requires-Dist: numpy (==1.*)
Requires-Dist: pandas (==1.*)
Requires-Dist: platformdirs (>=4.2.2,<5.0.0)
Requires-Dist: psycopg2-binary (>=2.9.9,<3.0.0)
Requires-Dist: pydash (>=8.0.1,<9.0.0)
Requires-Dist: python-dotenv (>=1.0.1,<2.0.0)
Requires-Dist: responses (>=0.25.3,<0.26.0)
Requires-Dist: sqlalchemy (>=1.0,<2.0)
Requires-Dist: typer[all] (>=0.16.0,<0.17.0)
